{
    "paths": {
        "common": "../../common/scripts",
        "jquery": "../../bower_components/jquery/jquery",
        "backbone": "../../bower_components/backbone/backbone",
        "underscore": "../../bower_components/underscore/underscore",
        "backbone.marionette": "../../bower_components/marionette/lib/backbone.marionette",
        "handlebars": "../../common/scripts/helpers/handlebars-loader"
    },
    "shim": {
        "templates": {
            "exports": "jst"
        },
        "underscore": {
            "exports": "_"
        },
        "backbone.marionette": {
            "deps": [
                "underscore",
                "jquery",
                "backbone"
            ],
            "exports": "Marionette"
        },
        "backbone": {
            "deps": [
                "underscore",
                "jquery"
            ],
            "exports": "Backbone"
        }
    }
}
